live_action/__init__.py
live_action/codec.py
live_action/evit.py
live_action/monarch.py
lvac-0.0.1.dist-info/METADATA
lvac-0.0.1.dist-info/WHEEL
lvac-0.0.1.dist-info/top_level.txt
lvac-0.0.1.dist-info/RECORD
