Metadata-Version: 2.4
Name: LVAC
Version: 0.0.1
Summary: Lightweight, Versatile, and Asymmetric Neural Codecs for Real-time Operation
Author-email: Dan Jacobellis <danjacobellis@utexas.edu>
Classifier: Programming Language :: Python :: 3
Classifier: Operating System :: OS Independent
Requires-Python: >=3.6
Requires-Dist: torch
Requires-Dist: einops
Requires-Dist: PyWavelets
Requires-Dist: timm
Requires-Dist: torchvision
Requires-Dist: pillow
